flask_saved/__init__.py
flask_saved/_compat.py
flask_saved/exception.py
flask_saved/providers/__init__.py
flask_saved/providers/local.py
flask_saved/providers/oss.py
Flask_Saved-1.0.5.dist-info/METADATA
Flask_Saved-1.0.5.dist-info/WHEEL
Flask_Saved-1.0.5.dist-info/top_level.txt
Flask_Saved-1.0.5.dist-info/RECORD
