Metadata-Version: 2.1
Name: Flask-Saved
Version: 1.0.5
Summary: flask文件存储器扩展
Home-page: UNKNOWN
Author: renjianguo
Author-email: renjianguo@kanhebei.cn
License: MIT
Platform: any
Classifier: Environment :: Web Environment
Classifier: Intended Audience :: Developers
Classifier: License :: OSI Approved :: BSD License
Classifier: Operating System :: OS Independent
Classifier: Programming Language :: Python
Classifier: Topic :: Internet :: WWW/HTTP :: Dynamic Content
Classifier: Topic :: Software Development :: Libraries :: Python Modules
Requires-Dist: Flask
Requires-Dist: oss2
